vanir-1.0.2.dist-info/METADATA
vanir-1.0.2.dist-info/WHEEL
vanir-1.0.2.dist-info/entry_points.txt
vanir-1.0.2.dist-info/licenses/LICENSE
vanir/__init__.py
vanir/cache/BUILD.bazel
vanir/cache/ecosystem_file_lists.py
vanir/code_extractors/BUILD.bazel
vanir/code_extractors/code_extractor.py
vanir/code_extractors/code_extractor_android.py
vanir/code_extractors/code_extractor_android_test.py
vanir/code_extractors/code_extractor_base.py
vanir/code_extractors/code_extractor_git.py
vanir/code_extractors/code_extractor_git_test.py
vanir/code_extractors/code_extractor_test.py
vanir/code_extractors/git_commit.py
vanir/code_extractors/git_commit_test.py
vanir/code_extractors/gitiles_commit.py
vanir/code_extractors/gitiles_commit_test.py
vanir/code_extractors/gob_commit.py
vanir/code_extractors/qualcomm_commit.py
vanir/code_extractors/qualcomm_commit_test.py
vanir/detector_common_flags.py
vanir/detector_common_flags_test.py
vanir/detector_runner.py
vanir/detector_runner_test.py
vanir/file_list_manager.py
vanir/file_list_manager_test.py
vanir/file_path_utils.py
vanir/hasher.py
vanir/hasher_test.py
vanir/integration_tests/BUILD.bazel
vanir/integration_tests/missing_patch_detection_hermetic_test.py
vanir/language_parsers/BUILD.bazel
vanir/language_parsers/abstract_language_parser.py
vanir/language_parsers/common.py
vanir/language_parsers/cpp/BUILD.bazel
vanir/language_parsers/cpp/cpp_parser.py
vanir/language_parsers/cpp/cpp_parser_test.py
vanir/language_parsers/cpp/parser_core.cc
vanir/language_parsers/cpp/parser_core.h
vanir/language_parsers/cpp/python/BUILD.bazel
vanir/language_parsers/cpp/python/parser_core.cc
vanir/language_parsers/java/BUILD.bazel
vanir/language_parsers/java/antlr4.external.bzl
vanir/language_parsers/java/java_parser.py
vanir/language_parsers/java/java_parser_test.py
vanir/language_parsers/java/parser_core.cc
vanir/language_parsers/java/parser_core.h
vanir/language_parsers/java/python/BUILD.bazel
vanir/language_parsers/java/python/parser_core.cc
vanir/language_parsers/language_parsers.py
vanir/normalizer.py
vanir/normalizer_test.py
vanir/osv_client.py
vanir/overwrite_specs_validity_test.py
vanir-1.0.2.dist-info/RECORD
