Metadata-Version: 2.4
Name: vanir
Version: 1.0.2
Summary: Vanir is a source code-based static analysis tool that automatically identifies the list of missing security patches in the target system. 
Keywords: static analysis,source code analysis,missing patch scanner
Author-Email: "Hyunwook (Wooky) Baek" <baekhw@google.com>, Duy Truong <duytruong@google.com>, Justin Dunlap <justindunlap@google.com>
Maintainer-Email: "Hyunwook (Wooky) Baek" <baekhw@google.com>, Duy Truong <duytruong@google.com>, Justin Dunlap <justindunlap@google.com>
License-Expression: GPL-3.0-only
Classifier: Programming Language :: Python :: 3
Classifier: Programming Language :: Python :: 3 :: Only
Classifier: Programming Language :: Python :: 3.9
Classifier: Programming Language :: Python :: 3.10
Classifier: Programming Language :: Python :: 3.11
Classifier: Programming Language :: Python :: 3.12
Classifier: Programming Language :: Python :: 3.13
Classifier: Operating System :: POSIX :: Linux
Classifier: Topic :: Security
Project-URL: Homepage, https://github.com/google/vanir
Project-URL: Issues, https://github.com/google/vanir/issues
Requires-Python: <3.14,>=3.9
Requires-Dist: absl-py<3,>=2.3.1
Requires-Dist: google-api-core[grpc]<3,>=2.25.1
Requires-Dist: google-auth<3,>=2.40.3
Requires-Dist: google-cloud-iam<3,>=2.19.1
Requires-Dist: google-cloud-storage<4,>=2.19.0
Requires-Dist: jinja2<4,>=3.1.6
Requires-Dist: jsonpath_ng<2,>=1.7.0
Requires-Dist: mmh3<6,>=5.2.0
Requires-Dist: osv==0.0.18; python_version < "3.10"
Requires-Dist: osv<0.1.0,>=0.0.21; python_version >= "3.10" and python_version < "3.13"
Requires-Dist: osv<1,>=0.1.2; python_version >= "3.13"
Requires-Dist: protobuf==3.20.3; python_version < "3.10"
Requires-Dist: protobuf<7,>=6.32.1; python_version >= "3.10"
Requires-Dist: python-dateutil<3,>=2.9.0.post0
Requires-Dist: requests<3,>=2.32.5
Requires-Dist: tenacity<10,>=9.1.2
Requires-Dist: typing-extensions<5,>=4.15.0
Requires-Dist: unidiff<1,>=0.7.5
